{"_id":{"$oid":"5e9f50ce12a0ed12d884fad8"},"Id":"e796c373-a8a3-40f5-9974-8a22e358acce","OperatorId":"a86a4e0a-b52a-4acd-bb12-b33205edd586","AccountId":"5264872569","Status":"In Progress","CreatedDate":"4/27/20 0:00","UpdatedDate":"4/17/20 10:31"}
{"_id":{"$oid":"5e9f50ce12a0ed12d884fad9"},"Id":"7999ea64-5dfe-4d75-aa86-98b2a2c2651f","OperatorId":"a86a4e0a-b52a-4acd-bb12-b33205edd586","AccountId":"5264872570","Status":"In Progress","CreatedDate":"4/27/20 0:00","UpdatedDate":"4/17/20 10:31"}
{"_id":{"$oid":"5e9f50ce12a0ed12d884fada"},"Id":"eb9887e1-2ae0-4372-a5a6-a84a844f2171","OperatorId":"a86a4e0a-b52a-4acd-bb12-b33205edd586","AccountId":"5264872571","Status":"In Progress","CreatedDate":"4/27/20 0:00","UpdatedDate":"4/17/20 10:31"}
{"_id":{"$oid":"5e9f50ce12a0ed12d884fadb"},"Id":"b3b77d42-01eb-4340-839f-a9f2b748c340","OperatorId":"a86a4e0a-b52a-4acd-bb12-b33205edd586","AccountId":"5264872572","Status":"In Progress","CreatedDate":"4/27/20 0:00","UpdatedDate":"4/17/20 10:31"}
{"_id":{"$oid":"5e9f50ce12a0ed12d884fadc"},"Id":"51d21ae0-fbd1-47e1-a8c6-db8fa3fab05a","OperatorId":"a86a4e0a-b52a-4acd-bb12-b33205edd586","AccountId":"5264872573","Status":"In Progress","CreatedDate":"4/27/20 0:00","UpdatedDate":"4/17/20 10:31"}
{"_id":{"$oid":"5e9f50ce12a0ed12d884fadd"},"Id":"a65cee6c-9356-40c8-af4c-6bbd677f66d0","OperatorId":"c8704727-a611-49dd-ac5d-28aa5ca5341b","AccountId":"5264872574","Status":"In Progress","CreatedDate":"4/27/20 0:00","UpdatedDate":"4/17/20 10:31"}
{"_id":{"$oid":"5e9f50ce12a0ed12d884fade"},"Id":"3afe3519-ffa0-4b3d-9531-88268060a9f6","OperatorId":"c8704727-a611-49dd-ac5d-28aa5ca5341b","AccountId":"5264872575","Status":"In Progress","CreatedDate":"4/27/20 0:00","UpdatedDate":"4/17/20 10:31"}
{"_id":{"$oid":"5e9f50ce12a0ed12d884fadf"},"Id":"f8da9dff-e476-4959-b3d9-db2c27cd12de","OperatorId":"c8704727-a611-49dd-ac5d-28aa5ca5341b","AccountId":"5264872576","Status":"In Progress","CreatedDate":"4/27/20 0:00","UpdatedDate":"4/17/20 10:31"}
{"_id":{"$oid":"5e9f50ce12a0ed12d884fae0"},"Id":"94e7a8d6-f7c6-4347-b7ab-9281331da556","OperatorId":"c8704727-a611-49dd-ac5d-28aa5ca5341b","AccountId":"5264872577","Status":"In Progress","CreatedDate":"4/27/20 0:00","UpdatedDate":"4/17/20 10:31"}
{"_id":{"$oid":"5e9f50ce12a0ed12d884fae1"},"Id":"1a2c2589-dbd5-4154-b423-a63cc4b5b26e","OperatorId":"c8704727-a611-49dd-ac5d-28aa5ca5341b","AccountId":"5264872578","Status":"In Progress","CreatedDate":"4/27/20 0:00","UpdatedDate":"4/17/20 10:31"}
{"_id":{"$oid":"5e9f50ce12a0ed12d884fae2"},"Id":"314c76dd-32e4-458f-9047-5f72a7111f63","OperatorId":"c8704727-a611-49dd-ac5d-28aa5ca5341b","AccountId":"5264872579","Status":"In Progress","CreatedDate":"4/27/20 0:00","UpdatedDate":"4/17/20 10:31"}
{"_id":{"$oid":"5e9f50ce12a0ed12d884fae3"},"Id":"6f67de82-f4bf-4f8a-a4b2-245f319eff8f","OperatorId":"c8704727-a611-49dd-ac5d-28aa5ca5341b","AccountId":"5264872580","Status":"In Progress","CreatedDate":"4/27/20 0:00","UpdatedDate":"4/17/20 10:31"}
{"_id":{"$oid":"5e9f50ce12a0ed12d884fae4"},"Id":"b22f829a-199f-4c64-aee5-27217b28dd7b","OperatorId":"69ae523e-5901-462d-b60f-92b4afed36a8","AccountId":"5264872581","Status":"In Progress","CreatedDate":"4/27/20 0:00","UpdatedDate":"4/17/20 10:31"}
{"_id":{"$oid":"5e9f50ce12a0ed12d884fae5"},"Id":"ff2abcfe-c59c-4818-8885-f2ce5e2673f4","OperatorId":"69ae523e-5901-462d-b60f-92b4afed36a8","AccountId":"5264872582","Status":"In Progress","CreatedDate":"4/27/20 0:00","UpdatedDate":"4/17/20 10:31"}
{"_id":{"$oid":"5e9f50ce12a0ed12d884fae6"},"Id":"11fcc8f2-adaf-45af-ad2b-05182601b111","OperatorId":"69ae523e-5901-462d-b60f-92b4afed36a8","AccountId":"5264872583","Status":"In Progress","CreatedDate":"4/27/20 0:00","UpdatedDate":"4/17/20 10:31"}
{"_id":{"$oid":"5e9f50ce12a0ed12d884fae7"},"Id":"a8a04551-13e5-4e3c-b44a-8a37f64fa972","OperatorId":"69ae523e-5901-462d-b60f-92b4afed36a8","AccountId":"5264872584","Status":"In Progress","CreatedDate":"4/27/20 0:00","UpdatedDate":"4/17/20 10:31"}
{"_id":{"$oid":"5e9f50ce12a0ed12d884fae8"},"Id":"a58a36f7-2ef3-4da7-ac43-d9ba11b76d55","OperatorId":"69ae523e-5901-462d-b60f-92b4afed36a8","AccountId":"5264872585","Status":"In Progress","CreatedDate":"4/27/20 0:00","UpdatedDate":"4/17/20 10:31"}
{"_id":{"$oid":"5e9f50ce12a0ed12d884fae9"},"Id":"e9194e06-4bbb-4784-9ad2-ac6f2782b702","OperatorId":"79bbdb08-4def-438d-914d-b8e0d8cdfdde","AccountId":"5264872586","Status":"In Progress","CreatedDate":"4/27/20 0:00","UpdatedDate":"4/17/20 10:31"}
{"_id":{"$oid":"5e9f50ce12a0ed12d884faea"},"Id":"29c76a8d-1807-4d11-bad5-b0c33910e983","OperatorId":"79bbdb08-4def-438d-914d-b8e0d8cdfdde","AccountId":"5264872587","Status":"In Progress","CreatedDate":"4/27/20 0:00","UpdatedDate":"4/17/20 10:31"}
